charset_generator/__init__.py
charset_generator/ai.py
charset_generator/yielding.py
charset_generator-1.0.1.dist-info/LICENSE
charset_generator-1.0.1.dist-info/METADATA
charset_generator-1.0.1.dist-info/WHEEL
charset_generator-1.0.1.dist-info/top_level.txt
charset_generator-1.0.1.dist-info/RECORD
