Metadata-Version: 2.2
Name: charset-generator
Version: 1.0.1
Summary: A charset generator for CTFs
Author: BlankAmber
License:                     GNU GENERAL PUBLIC LICENSE
Project-URL: Homepage, https://github.com/Samuel-BlankAmber/charset-generator
Project-URL: Repository, https://github.com/Samuel-BlankAmber/charset-generator
Project-URL: Issues, https://github.com/Samuel-BlankAmber/charset-generator/issues
Keywords: charset,generator,CTF
Requires-Python: >=3.7
License-File: LICENSE
Provides-Extra: yielding
Requires-Dist: keyboard<1,>=0.13; extra == "yielding"
Provides-Extra: ai
Requires-Dist: openai<2,>=1.65; extra == "ai"
